addlib/__init__.py
addlib/addlib-linux.so
addlib/addlib-win.so
addlib/gomethods.py
addlib/pywrap.py
addlib/lib.add/cities.data
addlib/lib.add/districts.data
addlib/lib.add/provinces.data
addlib-1.0.7.dist-info/DESCRIPTION.rst
addlib-1.0.7.dist-info/METADATA
addlib-1.0.7.dist-info/RECORD
addlib-1.0.7.dist-info/WHEEL
addlib-1.0.7.dist-info/metadata.json
addlib-1.0.7.dist-info/top_level.txt
addlib-1.0.7.dist-info/zip-safe
