Metadata-Version: 2.0
Name: addlib
Version: 1.0.7
Summary: Address Library (CN).
Home-page: UNKNOWN
Author: qx3501332
Author-email: x.qiu@qq.com
License: MIT License
Platform: UNKNOWN
Classifier: Development Status :: 4 - Beta
Classifier: Intended Audience :: Developers
Classifier: Operating System :: OS Independent
Classifier: Programming Language :: Python :: 3.6
Classifier: Topic :: Software Development :: Libraries :: Python Modules
